cesiumjs_anywidget/__init__.py
cesiumjs_anywidget/styles.css
cesiumjs_anywidget/widget.py
cesiumjs_anywidget/index.js
cesiumjs_anywidget-0.6.0.dist-info/METADATA
cesiumjs_anywidget-0.6.0.dist-info/WHEEL
cesiumjs_anywidget-0.6.0.dist-info/licenses/LICENSE
cesiumjs_anywidget-0.6.0.dist-info/RECORD
