Metadata-Version: 2.4
Name: cesiumjs-anywidget
Version: 0.6.0
Summary: A Jupyter widget for CesiumJS 3D globe visualization using anywidget
Project-URL: Homepage, https://github.com/Alex-PLACET/cesiumjs_anywidget
Project-URL: Repository, https://github.com/Alex-PLACET/cesiumjs_anywidget
Author: Alexis Placet
License:                                  Apache License
License-File: LICENSE
Classifier: Development Status :: 3 - Alpha
Classifier: Framework :: Jupyter
Classifier: Intended Audience :: Developers
Classifier: Intended Audience :: Science/Research
Classifier: License :: OSI Approved :: Apache Software License
Classifier: Programming Language :: Python :: 3
Classifier: Programming Language :: Python :: 3.8
Classifier: Programming Language :: Python :: 3.9
Classifier: Programming Language :: Python :: 3.10
Classifier: Programming Language :: Python :: 3.11
Classifier: Programming Language :: Python :: 3.12
Requires-Python: >=3.8
Requires-Dist: anywidget>=0.9.0
Requires-Dist: traitlets>=5.0.0
Provides-Extra: dev
Requires-Dist: jupyterlab>=4.0.0; extra == 'dev'
Requires-Dist: notebook>=7.0.0; extra == 'dev'
Requires-Dist: pytest-cov>=4.0.0; extra == 'dev'
Requires-Dist: pytest>=7.0.0; extra == 'dev'
